json2Xconverter/__init__.py
json2Xconverter/api_call_flat.py
json2Xconverter/x_converter.py
json2Xconverter-0.0.2.dist-info/LICENSE
json2Xconverter-0.0.2.dist-info/METADATA
json2Xconverter-0.0.2.dist-info/WHEEL
json2Xconverter-0.0.2.dist-info/top_level.txt
json2Xconverter-0.0.2.dist-info/RECORD
