Metadata-Version: 2.1
Name: json2Xconverter
Version: 0.0.2
Summary: Convert Api responst to CSV, XML, PDF or HTML file
Author: Snehal Borkar
Author-email: borkarsnehal60@gmail.com
License: UNKNOWN
Keywords: python
Platform: UNKNOWN
Classifier: Development Status :: 1 - Planning
Classifier: Intended Audience :: Developers
Classifier: Programming Language :: Python :: 3
Classifier: Operating System :: Unix
Classifier: Operating System :: MacOS :: MacOS X
Classifier: Operating System :: Microsoft :: Windows
License-File: LICENSE
Requires-Dist: pandas
Requires-Dist: json2xml
Requires-Dist: pdfkit
Requires-Dist: flatten-json
Requires-Dist: requests
Requires-Dist: json2html
